darktheme/__init__.py
darktheme/decorators.py
darktheme/decorators_pyqt6.py
darktheme/widget_template.py
darktheme/widget_template_pyqt6.py
pyqt_darktheme-1.3.dist-info/LICENSE
pyqt_darktheme-1.3.dist-info/METADATA
pyqt_darktheme-1.3.dist-info/WHEEL
pyqt_darktheme-1.3.dist-info/top_level.txt
pyqt_darktheme-1.3.dist-info/RECORD
