Metadata-Version: 2.1
Name: pyqt-darktheme
Version: 1.3
Summary: A PyQt dark theme, clickable widgets and cursor decorators
Home-page: https://github.com/Michael-Yongshi/Gui-Dark-Theme
Author: Michael-Yongshi
Author-email: 4registration@outlook.com
Classifier: Programming Language :: Python :: 3
Classifier: License :: OSI Approved :: GNU General Public License v3 or later (GPLv3+)
Classifier: Operating System :: OS Independent
Requires-Python: >=3.7
License-File: LICENSE
